LICENSE
MANIFEST.in
README.md
setup.py
xontrib/pyrtn.py
xontrib_pyrtn.egg-info/PKG-INFO
xontrib_pyrtn.egg-info/SOURCES.txt
xontrib_pyrtn.egg-info/dependency_links.txt
xontrib_pyrtn.egg-info/requires.txt
xontrib_pyrtn.egg-info/top_level.txt