Metadata-Version: 2.1
Name: xontrib-pyrtn
Version: 0.1.0
Summary: Store the python return value of commands for the session.
Home-page: https://github.com/dyuri/xontrib-pyrtn
Author: Gyuri Horák
Author-email: dyuri@horak.hu
License: MIT
Project-URL: Documentation, https://github.com/dyuri/xontrib-pyrtn/blob/master/README.md
Project-URL: Code, https://github.com/dyuri/xontrib-pyrtn
Project-URL: Issue tracker, https://github.com/dyuri/xontrib-pyrtn/issues
Platform: any
Classifier: Programming Language :: Python :: 3
Classifier: Programming Language :: Python :: 3.6
Classifier: Programming Language :: Python :: 3.7
Classifier: Programming Language :: Python :: 3.8
Classifier: Programming Language :: Python :: 3.9
Classifier: License :: OSI Approved :: MIT License
Classifier: Operating System :: OS Independent
Classifier: Topic :: System :: Shells
Classifier: Topic :: System :: System Shells
Classifier: Topic :: Terminals
Requires-Python: >=3.6
License-File: LICENSE
